{
  "presetName": "aod m/m ham",
  "presetNotes": "",
  "equipmentSlots": [
    {
      "label": "vestmenthood",
      "image": "https://img.pvme.io/images/EVh5SwD.png",
      "name": "Vestments of havoc hood",
      "breakdownNotes": "",
      "wikiLink": "https://runescape.wiki/w/Vestments_of_havoc_hood"
    },
    {
      "label": "kalzuk",
      "image": "https://img.pvme.io/images/jcfkzGn.png",
      "name": "Igneous Kal-Zuk",
      "breakdownNotes": "",
      "wikiLink": "https://runescape.wiki/w/Igneous_Kal-Zuk"
    },
    {
      "label": "eofblackunorn",
      "image": "https://img.pvme.io/images/jRuWtdl.png",
      "name": "EoF - Statius's warhammer",
      "breakdownNotes": "",
      "wikiLink": "https://runescape.wiki/w/Statius%27s_warhammer"
    },
    {
      "label": "zekkil",
      "image": "https://img.pvme.io/images/aKEG5mi.png",
      "name": "Ek-ZekKil",
      "breakdownNotes": "",
      "wikiLink": "https://runescape.wiki/w/Ek-ZekKil"
    },
    {
      "label": "vestmentbody",
      "image": "https://img.pvme.io/images/E5ptfu6.png",
      "name": "Vestments of havoc robe top",
      "breakdownNotes": "",
      "wikiLink": "https://runescape.wiki/w/Vestments_of_havoc_robe_top"
    },
    {
      "name": "",
      "image": "",
      "label": "",
      "breakdownNotes": ""
    },
    {
      "label": "vestmentlegs",
      "image": "https://img.pvme.io/images/mz7GwWF.png",
      "name": "Vestments of havoc robe bottom",
      "breakdownNotes": "",
      "wikiLink": "https://runescape.wiki/w/Vestments_of_havoc_robe_bottom"
    },
    {
      "label": "dtb",
      "image": "https://img.pvme.io/images/ia3JNEm.png",
      "name": "Deathtouched bracelet",
      "breakdownNotes": "",
      "wikiLink": "https://runescape.wiki/w/Deathtouched_bracelet"
    },
    {
      "label": "vestmentboots",
      "image": "https://img.pvme.io/images/FarIA5V.png",
      "name": "Vestments of havoc boots",
      "breakdownNotes": "",
      "wikiLink": "https://runescape.wiki/w/Vestments_of_havoc_boots"
    },
    {
      "label": "reaverring",
      "image": "https://img.pvme.io/images/cnIOClx.png",
      "name": "Reaver's ring",
      "breakdownNotes": "",
      "wikiLink": "https://runescape.wiki/w/Reaver's_ring"
    },
    {
      "label": "pernixquiver",
      "image": "https://img.pvme.io/images/b3geFp8.png",
      "name": "Pernix's Quiver",
      "breakdownNotes": "Hydrix Bak",
      "wikiLink": "https://runescape.wiki/w/Pernix's_Quiver"
    },
    {
      "label": "zerk",
      "image": "https://img.pvme.io/images/Fme45Ts.png",
      "name": "Berserker aura",
      "breakdownNotes": "",
      "wikiLink": "https://runescape.wiki/w/Berserker_aura"
    },
    {
      "label": "grim",
      "image": "https://img.pvme.io/images/eAO0PdY.png",
      "name": "Erethdor's grimoire",
      "breakdownNotes": "",
      "wikiLink": "https://runescape.wiki/w/Erethdor's_grimoire"
    }
  ],
  "inventorySlots": [
    {
      "label": "etectohelm",
      "image": "https://img.pvme.io/images/iPtkkKN.png",
      "name": "Elite tectonic mask",
      "breakdownNotes": "",
      "wikiLink": "https://runescape.wiki/w/Elite_tectonic_mask",
      "selected": false
    },
    {
      "label": "odetodeceit",
      "image": "https://img.pvme.io/images/8WKmBCfI34.png",
      "name": "Ode to Deceit",
      "breakdownNotes": "",
      "wikiLink": "https://runescape.wiki/w/Ode_to_Deceit",
      "selected": false
    },
    {
      "label": "roarofawakening",
      "image": "https://img.pvme.io/images/nCmqhfpcHo.png",
      "name": "Roar of Awakening",
      "breakdownNotes": "",
      "wikiLink": "https://runescape.wiki/w/Roar_of_Awakening",
      "selected": false
    },
    {
      "label": "jelly",
      "image": "https://img.pvme.io/images/RD2LyxF.png",
      "name": "Blue blubber jellyfish",
      "breakdownNotes": "",
      "wikiLink": "https://runescape.wiki/w/Blue_blubber_jellyfish",
      "selected": false
    },
    {
      "label": "gbrew",
      "image": "https://img.pvme.io/images/dPf2fLt.png",
      "name": "Super Guthix brew flask (6)",
      "breakdownNotes": "",
      "wikiLink": "https://runescape.wiki/w/Super_Guthix_brew_flask#(6)",
      "selected": false
    },
    {
      "label": "salve",
      "image": "https://img.pvme.io/images/9GP63eS.png",
      "name": "Elder overload salve (6)",
      "breakdownNotes": "",
      "wikiLink": "https://runescape.wiki/w/Elder_overload_salve#(6)",
      "selected": false
    },
    {
      "label": "zemouregalsnexus",
      "image": "https://img.pvme.io/images/3pFXvMR.png",
      "name": "Zemouregal's Nexus",
      "breakdownNotes": "",
      "wikiLink": "https://runescape.wiki/w/Zemouregal%27s_nexus",
      "selected": false
    },
    {
      "label": "etectotop",
      "image": "https://img.pvme.io/images/NftWcLQ.png",
      "name": "Elite tectonic robe top",
      "breakdownNotes": "",
      "wikiLink": "https://runescape.wiki/w/Elite_tectonic_robe_top",
      "selected": false
    },
    {
      "label": "lengmh",
      "image": "https://img.pvme.io/images/wFdHN9C.png",
      "name": "Dark Shard of Leng",
      "breakdownNotes": "",
      "wikiLink": "https://runescape.wiki/w/Dark_Shard_of_Leng",
      "selected": false
    },
    {
      "label": "lengoh",
      "image": "https://img.pvme.io/images/LAVYvrE.png",
      "name": "Dark Sliver of Leng",
      "breakdownNotes": "",
      "wikiLink": "https://runescape.wiki/w/Dark_Sliver_of_Leng",
      "selected": false
    },
    {
      "label": "jelly",
      "image": "https://img.pvme.io/images/RD2LyxF.png",
      "name": "Blue blubber jellyfish",
      "breakdownNotes": "",
      "wikiLink": "https://runescape.wiki/w/Blue_blubber_jellyfish",
      "selected": false
    },
    {
      "label": "gbrew",
      "image": "https://img.pvme.io/images/dPf2fLt.png",
      "name": "Super Guthix brew flask (6)",
      "breakdownNotes": "",
      "wikiLink": "https://runescape.wiki/w/Super_Guthix_brew_flask#(6)",
      "selected": false
    },
    {
      "label": "spiritual",
      "image": "https://img.pvme.io/images/PFLToHh.png",
      "name": "Spiritual prayer (6)",
      "breakdownNotes": "",
      "wikiLink": "https://runescape.wiki/w/Spiritual_prayer#(6)",
      "selected": false
    },
    {
      "label": "graspingpouchblack",
      "image": "https://img.pvme.io/images/hxQ7DadacM.png",
      "name": "Grasping rune pouch (black)",
      "breakdownNotes": "Blood | Astral | Body | Soul",
      "wikiLink": "https://runescape.wiki/w/Grasping_rune_pouch_(black)",
      "selected": false
    },
    {
      "label": "etectolegs",
      "image": "https://img.pvme.io/images/0TXtWf2.png",
      "name": "Elite tectonic robe bottom",
      "breakdownNotes": "",
      "wikiLink": "https://runescape.wiki/w/Elite_tectonic_robe_bottom",
      "selected": false
    },
    {
      "label": "fsoa",
      "image": "https://img.pvme.io/images/AI12yBk.png",
      "name": "Fractured Staff of Armadyl",
      "breakdownNotes": "",
      "wikiLink": "https://runescape.wiki/w/Fractured_Staff_of_Armadyl",
      "selected": false
    },
    {
      "label": "dummy",
      "image": "https://img.pvme.io/images/Dgtgp4n.png",
      "name": "Combat dummy MKII",
      "breakdownNotes": "",
      "wikiLink": "https://runescape.wiki/w/Combat_dummy_MKII",
      "selected": false
    },
    {
      "label": "excal",
      "image": "https://img.pvme.io/images/nC5xTAR.png",
      "name": "Enhanced excalibur",
      "breakdownNotes": "",
      "wikiLink": "https://runescape.wiki/w/Enhanced_excalibur",
      "selected": false
    },
    {
      "label": "timerune",
      "image": "https://img.pvme.io/images/uhPTmJEBGW.png",
      "name": "Time rune",
      "breakdownNotes": "",
      "wikiLink": "https://runescape.wiki/w/Time_rune",
      "selected": false
    },
    {
      "label": "renewal4",
      "image": "https://img.pvme.io/images/IqAjWRF.png",
      "name": "Adrenaline renewal potion (4)",
      "breakdownNotes": "",
      "wikiLink": "https://runescape.wiki/w/Adrenaline_renewal_potion#(4)",
      "selected": false
    },
    {
      "label": "graspingpouchpink",
      "image": "https://img.pvme.io/images/cMrBUILe61.png",
      "name": "Grasping rune pouch (pink)",
      "breakdownNotes": "Death | Earth | Law | Cosmic",
      "wikiLink": "https://runescape.wiki/w/Grasping_rune_pouch_(pink)",
      "selected": false
    },
    {
      "label": "enhancedblastdiff",
      "image": "https://img.pvme.io/images/KUGqEdN.png",
      "name": "Enhanced blast diffusion boots",
      "breakdownNotes": "",
      "wikiLink": "https://runescape.wiki/w/Enhanced_blast_diffusion_boots",
      "selected": false
    },
    {
      "label": "ecb",
      "image": "https://img.pvme.io/images/n98Fmxx.png",
      "name": "Eldritch crossbow",
      "breakdownNotes": "Caroming 4",
      "wikiLink": "https://runescape.wiki/w/Eldrich_crossbow",
      "selected": false
    },
    {
      "label": "eofred",
      "image": "https://img.pvme.io/images/JMC7t7Y.png",
      "name": "EoF - Dragon claws",
      "breakdownNotes": "",
      "wikiLink": "https://runescape.wiki/w/Dragon_claws",
      "selected": false
    },
    {
      "label": "eofpurple",
      "image": "https://img.pvme.io/images/nu7QSbh.png",
      "name": "EoF - Guthix staff / Zamorak staff",
      "breakdownNotes": "",
      "wikiLink": "https://runescape.wiki/w/Guthix_staff",
      "selected": false
    },
    {
      "label": "accel4",
      "image": "https://img.pvme.io/images/I6HFjyN.png",
      "name": "Powerburst of acceleration (4)",
      "breakdownNotes": "",
      "wikiLink": "https://runescape.wiki/w/Powerburst_of_acceleration#(4)",
      "selected": false
    },
    {
      "label": "vuln",
      "image": "https://img.pvme.io/images/2vI8jNm.png",
      "name": "Vulnerabilty bombs",
      "breakdownNotes": "",
      "wikiLink": "https://runescape.wiki/w/Vulnerabilty_bombs",
      "selected": false
    },
    {
      "label": "graspingpouchblue",
      "image": "https://img.pvme.io/images/1JjM2xHyOj.png",
      "name": "Grasping rune pouch (blue)",
      "breakdownNotes": "Chaos | Air | Water | Fire",
      "wikiLink": "https://runescape.wiki/w/Grasping_rune_pouch_(blue)",
      "selected": false
    }
  ],
  "relics": {
    "primaryRelics": [
      {
        "image": "https://i.imgur.com/Gfdc9u6.png",
        "name": "Conservation of Energy",
        "breakdownNotes": "",
        "label": "conservationofenergy",
        "energy": 350
      },
      {
        "image": "https://i.imgur.com/xXWYCHG.png",
        "name": "Berserkers Fury",
        "breakdownNotes": "",
        "label": "berserkersfury",
        "energy": 250
      },
      {
        "image": "https://i.imgur.com/7e6Juey.png",
        "name": "Font of Life",
        "breakdownNotes": "",
        "label": "fontoflife",
        "energy": 50
      }
    ],
    "alternativeRelics": [
      {
        "image": "",
        "name": "",
        "breakdownNotes": "",
        "label": ""
      },
      {
        "image": "",
        "name": "",
        "breakdownNotes": "",
        "label": ""
      }
    ]
  },
  "familiars": {
    "primaryFamiliars": [
      {
        "image": "https://i.imgur.com/Gg4oxrm.png",
        "name": "Ripper Demon",
        "breakdownNotes": "",
        "label": "ripperdemon"
      }
    ],
    "alternativeFamiliars": [
      {
        "image": "",
        "name": "",
        "breakdownNotes": "",
        "label": ""
      },
      {
        "image": "",
        "name": "",
        "breakdownNotes": "",
        "label": ""
      },
      {
        "image": "",
        "name": "",
        "breakdownNotes": "",
        "label": ""
      }
    ]
  }
}